{
  "$schema": "./node_modules/@angular/cli/lib/config/schema.json",
  "version": 1,
  "newProjectRoot": "projects",
  "projects": {
    "JWebMP": {
      "projectType": "application",
      "schematics": {
        "@schematics/angular:component": {
          "inlineTemplate": true,
          "inlineStyle": true,
          "style": "scss",
          "skipTests": true
        },
        "@schematics/angular:class": {
          "skipTests": true
        },
        "@schematics/angular:directive": {
          "skipTests": true
        },
        "@schematics/angular:guard": {
          "skipTests": true
        },
        "@schematics/angular:interceptor": {
          "skipTests": true
        },
        "@schematics/angular:pipe": {
          "skipTests": true
        },
        "@schematics/angular:resolver": {
          "skipTests": true
        },
        "@schematics/angular:service": {
          "skipTests": true
        },
        "@schematics/angular:application": {
          "strict": true
        }
      },
      "root": "",
      "sourceRoot": "src",
      "prefix": "app",
      "architect": {
        "build": {
          "builder": "@angular-devkit/build-angular:application",
          "options": {
            "outputPath": "dist/jwebmp",
            "index": "src/index.html",
            "browser": /*MainTSFile*/,
            "polyfills": [
            ],
            "tsConfig": "tsconfig.app.json",
            "inlineStyleLanguage": "scss",
            "assets":  /*BuildAssets*/,
            "styles": /*BuildStylesSCSS*/ ,
            "scripts": /*BuildScripts*/
          },
          "configurations": {
            "production": {
              "vendorChunk": true,
              "optimization": {
                "scripts": true,
                "styles": {
                  "minify": true,
                  "inlineCritical": false
                },
                "fonts": true
              },
              "budgets": [
                {
                  "type": "initial",
                  "maximumWarning": "8500kb",
                  "maximumError": "25mb"
                },
                {
                  "type": "anyComponentStyle",
                  "maximumWarning": "20kb",
                  "maximumError": "40kb"
                }
              ],
              "outputHashing": "all"
            },
            "development": {
              "buildOptimizer": false,
              "optimization": false,
              "vendorChunk": true,
              "extractLicenses": false,
              "sourceMap": true,
              "namedChunks": true
            }
          },
          "defaultConfiguration": "development"
        },
        "serve": {
          "builder": "@angular-devkit/build-angular:dev-server",
          "configurations": {
            "production": {
              "browserTarget": "JWebMP:build:production"
            },
            "development": {
              "browserTarget": "JWebMP:build:development"
            }
          },
          "defaultConfiguration": "development"
        },
        "extract-i18n": {
          "builder": "@angular-devkit/build-angular:extract-i18n",
          "options": {
            "browserTarget": "JWebMP:build"
          }
        }
      }
    }
  },
  "defaultProject": "JWebMP"
}
